WeiruanGuanfangNetCoreZhinan20171224/README.md
WeiruanGuanfangNetCoreZhinan20171224/__init__.py
WeiruanGuanfangNetCoreZhinan20171224/__main__.py
WeiruanGuanfangNetCoreZhinan20171224/file.epub
WeiruanGuanfangNetCoreZhinan20171224/index.html
WeiruanGuanfangNetCoreZhinan20171224/css/__init__.py
WeiruanGuanfangNetCoreZhinan20171224/css/annotations.css
WeiruanGuanfangNetCoreZhinan20171224/css/main.css
WeiruanGuanfangNetCoreZhinan20171224/css/normalize.css
WeiruanGuanfangNetCoreZhinan20171224/css/popup.css
WeiruanGuanfangNetCoreZhinan20171224/font/__init__.py
WeiruanGuanfangNetCoreZhinan20171224/font/fontello.eot
WeiruanGuanfangNetCoreZhinan20171224/font/fontello.svg
WeiruanGuanfangNetCoreZhinan20171224/font/fontello.ttf
WeiruanGuanfangNetCoreZhinan20171224/font/fontello.woff
WeiruanGuanfangNetCoreZhinan20171224/img/__init__.py
WeiruanGuanfangNetCoreZhinan20171224/img/annotator-glyph-sprite.png
WeiruanGuanfangNetCoreZhinan20171224/img/annotator-icon-sprite.png
WeiruanGuanfangNetCoreZhinan20171224/img/apple-touch-icon.png
WeiruanGuanfangNetCoreZhinan20171224/img/cancelfullscreen.png
WeiruanGuanfangNetCoreZhinan20171224/img/close.png
WeiruanGuanfangNetCoreZhinan20171224/img/fullscreen.png
WeiruanGuanfangNetCoreZhinan20171224/img/loader.gif
WeiruanGuanfangNetCoreZhinan20171224/img/menu-icon.png
WeiruanGuanfangNetCoreZhinan20171224/img/save.png
WeiruanGuanfangNetCoreZhinan20171224/img/saved.png
WeiruanGuanfangNetCoreZhinan20171224/img/settings-s.png
WeiruanGuanfangNetCoreZhinan20171224/img/settings.png
WeiruanGuanfangNetCoreZhinan20171224/img/star.png
WeiruanGuanfangNetCoreZhinan20171224/js/__init__.py
WeiruanGuanfangNetCoreZhinan20171224/js/epub.js
WeiruanGuanfangNetCoreZhinan20171224/js/epub.min.js
WeiruanGuanfangNetCoreZhinan20171224/js/epub.min.map
WeiruanGuanfangNetCoreZhinan20171224/js/hooks.min.js
WeiruanGuanfangNetCoreZhinan20171224/js/hooks.min.map
WeiruanGuanfangNetCoreZhinan20171224/js/reader.js
WeiruanGuanfangNetCoreZhinan20171224/js/reader.js.map
weiruan_guanfang_net_core_zhinan_20171224-2024.3.2.0.dist-info/METADATA
weiruan_guanfang_net_core_zhinan_20171224-2024.3.2.0.dist-info/WHEEL
weiruan_guanfang_net_core_zhinan_20171224-2024.3.2.0.dist-info/entry_points.txt
weiruan_guanfang_net_core_zhinan_20171224-2024.3.2.0.dist-info/top_level.txt
weiruan_guanfang_net_core_zhinan_20171224-2024.3.2.0.dist-info/RECORD
